pypiglatin/__init__.py
pypiglatin-0.1.2.dist-info/WHEEL
pypiglatin-0.1.2.dist-info/METADATA
pypiglatin-0.1.2.dist-info/RECORD
