Metadata-Version: 2.1
Name: pypiglatin
Version: 0.1.2
Summary: A module that can convert words or strings of words from English to Pig Latin.
Home-page: https://github.com/Owen7000/pypiglatin
License: GPL-3.0-only
Author: Owen Plimer
Author-email: o.plimer@outlook.com
Maintainer: Sonosus
Maintainer-email: sonosusoshwa@gmail.com
Requires-Python: >=3.10,<4.0
Classifier: License :: OSI Approved :: GNU General Public License v3 (GPLv3)
Classifier: Programming Language :: Python :: 3
Classifier: Programming Language :: Python :: 3.10
Classifier: Programming Language :: Python :: 3.11
Project-URL: Repository, https://github.com/Owen7000/pypiglatin
